KratosMultiphysics/MedApplication/__init__.py
KratosMultiphysics/MedApplication/python_registry_lists.py
KratosMultiphysics/MedApplication/modelers/import_med_modeler.py
KratosMultiphysics/.libs/KratosMedApplication.pyd
KratosMultiphysics/.libs/KratosMedCore.dll
KratosMultiphysics/.libs/KratosMedCore.lib
KratosMultiphysics/.libs/hdf5.dll
KratosMultiphysics/.libs/hdf5_hl.dll
KratosMultiphysics/.libs/hdf5_tools.dll
KratosMultiphysics/.libs/medC.dll
KratosMultiphysics/.libs/medimport.dll
kratosmedapplication-10.4.0.dist-info/METADATA
kratosmedapplication-10.4.0.dist-info/WHEEL
kratosmedapplication-10.4.0.dist-info/RECORD
